ollama_proxy/__init__.py
ollama_proxy/config.py
ollama_proxy/define.py
ollama_proxy/main.py
ollama_proxy/models.py
ollama_proxy/services/__init__.py
ollama_proxy/services/base.py
ollama_proxy/services/deepseek.py
ollama_proxy/services/glm.py
ollama_proxy-0.2.0.dist-info/LICENSE
ollama_proxy-0.2.0.dist-info/METADATA
ollama_proxy-0.2.0.dist-info/WHEEL
ollama_proxy-0.2.0.dist-info/entry_points.txt
ollama_proxy-0.2.0.dist-info/RECORD
